LICENSE
MANIFEST.in
README.md
setup.py
promoted/__init__.py
promoted.egg-info/PKG-INFO
promoted.egg-info/SOURCES.txt
promoted.egg-info/dependency_links.txt
promoted.egg-info/top_level.txt